django_presentation/__init__.py
django_presentation/utils.py
django_presentation/version.py
django_presentation/favicon/__init__.py
django_presentation/favicon/middleware.py
django_presentation/favicon/views.py
django_presentation/favicon/static/images/favicon/favicon_dev.ico
django_presentation/favicon/static/images/favicon/favicon_local.ico
django_presentation/favicon/static/images/favicon/favicon_test.ico
django_presentation/forms/Button.py
django_presentation/forms/ErrorMessages.py
django_presentation/forms/Field.py
django_presentation/forms/FormPresentation.py
django_presentation/forms/FormPresentationBoundItem.py
django_presentation/forms/FormPresentationItem.py
django_presentation/forms/Html.py
django_presentation/forms/Subform.py
django_presentation/forms/__init__.py
django_presentation/forms/fields/GroupedModelChoiceField.py
django_presentation/forms/fields/TypedChoiceField.py
django_presentation/forms/fields/__init__.py
django_presentation/forms/styles/formPresentation_button.scss
django_presentation/forms/styles/formPresentation_errors.scss
django_presentation/forms/styles/formPresentation_field.scss
django_presentation/forms/styles/formPresentation_item.scss
django_presentation/forms/templates/formPresentation/button.html
django_presentation/forms/templates/formPresentation/errors.html
django_presentation/forms/templates/formPresentation/field.html
django_presentation/forms/templates/formPresentation/field.inlineCheckbox.html
django_presentation/forms/widgets/ChoicesRadioSelect.py
django_presentation/forms/widgets/StyledUnknownYesNoSelect.py
django_presentation/forms/widgets/__init__.py
django_presentation/messages/__init__.py
django_presentation/messages/contextProcessors.py
django_presentation/messages/messageBox.py
django_presentation/messages/styles/messages_messageBox.scss
django_presentation/messages/templates/messages/messageBox.html
django_presentation/messages/templatetags/__init__.py
django_presentation-0.0.8.dist-info/DESCRIPTION.rst
django_presentation-0.0.8.dist-info/METADATA
django_presentation-0.0.8.dist-info/RECORD
django_presentation-0.0.8.dist-info/WHEEL
django_presentation-0.0.8.dist-info/metadata.json
django_presentation-0.0.8.dist-info/top_level.txt
