Metadata-Version: 2.0
Name: django-presentation
Version: 0.0.8
Summary: Adding some presentation functionality to the Python side of Django
Home-page: http://github.com/adamkerz/django-presentation
Author: Adam Kerz
Author-email: github@kerz.id.au
License: BSD 3-Clause
Keywords: django
Platform: UNKNOWN
Classifier: Development Status :: 4 - Beta
Classifier: Intended Audience :: Developers
Classifier: Natural Language :: English
Classifier: License :: OSI Approved :: BSD License
Classifier: Operating System :: OS Independent
Classifier: Programming Language :: Python
Classifier: Programming Language :: Python :: 2
Classifier: Programming Language :: Python :: 2.7
Classifier: Programming Language :: Python :: 3
Classifier: Programming Language :: Python :: 3.4
Classifier: Topic :: Software Development :: Libraries :: Python Modules
Requires-Dist: django
